gcp_mixed_logging/__init__.py
gcp_mixed_logging/logger_v2.py
gcp_mixed_logging-0.0.9.dist-info/LICENSE
gcp_mixed_logging-0.0.9.dist-info/METADATA
gcp_mixed_logging-0.0.9.dist-info/WHEEL
gcp_mixed_logging-0.0.9.dist-info/top_level.txt
gcp_mixed_logging-0.0.9.dist-info/RECORD
