Metadata-Version: 2.1
Name: gcp-mixed-logging
Version: 0.0.9
Summary: write log to cloud logging or fluentd, for app in gcp
Home-page: https://github.com/wbchn/gcp-mixed-logging
Download-URL: http://pypi.python.org/pypi/gcp-mixed-logging/
Author: wb
Author-email: wbin.chn@gmail.com
Maintainer: wbchn
Maintainer-email: wbin.chn@gmail.com
License: MIT
Classifier: License :: OSI Approved :: MIT License
Classifier: Programming Language :: Python
Classifier: Programming Language :: Python :: 3
Classifier: Programming Language :: Python :: 3.7
Classifier: Programming Language :: Python :: 3.8
Classifier: Programming Language :: Python :: 3.9
Classifier: Intended Audience :: Developers
Requires-Python: >=3.7.0
License-File: LICENSE
Requires-Dist: fluent-logger (==0.10.0)
Requires-Dist: google-cloud-logging (==3.2.5)
Requires-Dist: cached-property (>=1.5.0) ; python_version <= "3.7"
